{
    "sourceFile": "e_commerce/templates/home/confirmation_commande.html",
    "activeCommit": 0,
    "commits": [
        {
            "activePatchIndex": 8,
            "patches": [
                {
                    "date": 1740075666055,
                    "content": "Index: \n===================================================================\n--- \n+++ \n"
                },
                {
                    "date": 1740086590128,
                    "content": "Index: \n===================================================================\n--- \n+++ \n@@ -1,52 +1,75 @@\n <!DOCTYPE html>\r\n <html>\r\n <head>\r\n     <style>\r\n-        body { font-family: Arial, sans-serif; line-height: 1.6; }\r\n-        .container { max-width: 600px; margin: 0 auto; padding: 20px; }\r\n-        .header { text-align: center; padding: 20px 0; }\r\n-        .order-details { margin: 20px 0; }\r\n-        .product-list { margin: 20px 0; }\r\n-        .product-item { padding: 10px 0; border-bottom: 1px solid #eee; }\r\n-        .total { margin-top: 20px; font-weight: bold; }\r\n-        .footer { text-align: center; margin-top: 30px; color: #666; }\r\n+        body { \r\n+            font-family: Arial, sans-serif;\r\n+            line-height: 1.6;\r\n+            color: #333;\r\n+        }\r\n+        .container {\r\n+            max-width: 600px;\r\n+            margin: 0 auto;\r\n+            padding: 20px;\r\n+        }\r\n+        .header {\r\n+            background-color: #f8f9fa;\r\n+            padding: 20px;\r\n+            text-align: center;\r\n+            border-radius: 5px;\r\n+        }\r\n+        .order-details {\r\n+            margin: 20px 0;\r\n+            padding: 15px;\r\n+            border: 1px solid #ddd;\r\n+            border-radius: 5px;\r\n+        }\r\n+        .product-item {\r\n+            padding: 10px 0;\r\n+            border-bottom: 1px solid #eee;\r\n+        }\r\n+        .total {\r\n+            margin-top: 20px;\r\n+            padding: 15px;\r\n+            background-color: #f8f9fa;\r\n+            border-radius: 5px;\r\n+            font-weight: bold;\r\n+        }\r\n     </style>\r\n </head>\r\n <body>\r\n     <div class=\"container\">\r\n         <div class=\"header\">\r\n             <h1>Confirmation de commande</h1>\r\n-            <p>Merci pour votre commande!</p>\r\n+            <p>Bonjour {{ user.get_full_name }},</p>\r\n         </div>\r\n \r\n         <div class=\"order-details\">\r\n-            <p><strong>Référence:</strong> {{ commande.reference }}</p>\r\n+            <h2>Détails de votre commande #{{ commande.id }}</h2>\r\n             <p><strong>Date:</strong> {{ date }}</p>\r\n-            <p><strong>Mode de paiement:</strong> {{ mode_paiement }}</p>\r\n+            <p><strong>Mode de paiement:</strong> {{ commande.get_payment_method_display }}</p>\r\n         </div>\r\n \r\n-        <div class=\"product-list\">\r\n-            <h2>Articles commandés:</h2>\r\n-            {% for article in articles %}\r\n-            <div class=\"product-item\">\r\n-                <p>\r\n-                    <strong>{{ article.produit.nom }}</strong><br>\r\n-                    Quantité: {{ article.quantite }}<br>\r\n-                    Prix unitaire: {{ article.prix_unitaire }}FCFA<br>\r\n-                    Total: {{ article.prix_total }} FCFA\r\n-                </p>\r\n-            </div>\r\n-            {% endfor %}\r\n+        <h3>Articles commandés:</h3>\r\n+        {% for line in order_lines %}\r\n+        <div class=\"product-item\">\r\n+            <p>\r\n+                <strong>{{ line.product.name }}</strong><br>\r\n+                Quantité: {{ line.quantity }}<br>\r\n+                Prix unitaire: {{ line.unit_price }}FCFA<br>\r\n+                Total ligne: {{ line.line_total }}fcfa\r\n+            </p>\r\n         </div>\r\n+        {% endfor %}\r\n \r\n         <div class=\"total\">\r\n             <p>Total de la commande: {{ total }}FCFA</p>\r\n         </div>\r\n \r\n-        <div class=\"footer\">\r\n-            <p>En cas de question, n'hésitez pas à nous contacter.</p>\r\n+        <div style=\"text-align: center; margin-top: 30px; color: #666;\">\r\n             <p>Merci de votre confiance!</p>\r\n+            <p>Si vous avez des questions, n'hésitez pas à nous contacter.</p>\r\n         </div>\r\n     </div>\r\n </body>\r\n </html>\n\\ No newline at end of file\n"
                },
                {
                    "date": 1740086699520,
                    "content": "Index: \n===================================================================\n--- \n+++ \n@@ -0,0 +1,75 @@\n+<!DOCTYPE html>\r\n+<html>\r\n+<head>\r\n+    <style>\r\n+        body { \r\n+            font-family: Arial, sans-serif;\r\n+            line-height: 1.6;\r\n+            color: #333;\r\n+        }\r\n+        .container {\r\n+            max-width: 600px;\r\n+            margin: 0 auto;\r\n+            padding: 20px;\r\n+        }\r\n+        .header {\r\n+            background-color:rgb(233, 17, 17);\r\n+            padding: 20px;\r\n+            text-align: center;\r\n+            border-radius: 5px;\r\n+        }\r\n+        .order-details {\r\n+            margin: 20px 0;\r\n+            padding: 15px;\r\n+            border: 1px solid #ddd;\r\n+            border-radius: 5px;\r\n+        }\r\n+        .product-item {\r\n+            padding: 10px 0;\r\n+            border-bottom: 1px solid #eee;\r\n+        }\r\n+        .total {\r\n+            margin-top: 20px;\r\n+            padding: 15px;\r\n+            background-color:rgb(223, 10, 10);\r\n+            border-radius: 5px;\r\n+            font-weight: bold;\r\n+        }\r\n+    </style>\r\n+</head>\r\n+<body>\r\n+    <div class=\"container\">\r\n+        <div class=\"header\">\r\n+            <h1>Confirmation de commande</h1>\r\n+            <p>Bonjour {{ user.get_full_name }},</p>\r\n+        </div>\r\n+\r\n+        <div class=\"order-details\">\r\n+            <h2>Détails de votre commande #{{ commande.id }}</h2>\r\n+            <p><strong>Date:</strong> {{ date }}</p>\r\n+            <p><strong>Mode de paiement:</strong> {{ commande.get_payment_method_display }}</p>\r\n+        </div>\r\n+\r\n+        <h3>Articles commandés:</h3>\r\n+        {% for line in order_lines %}\r\n+        <div class=\"product-item\">\r\n+            <p>\r\n+                <strong>{{ line.product.name }}</strong><br>\r\n+                Quantité: {{ line.quantity }}<br>\r\n+                Prix unitaire: {{ line.unit_price }}FCFA<br>\r\n+                Total ligne: {{ line.line_total }}fcfa\r\n+            </p>\r\n+        </div>\r\n+        {% endfor %}\r\n+\r\n+        <div class=\"total\">\r\n+            <p>Total de la commande: {{ total }}FCFA</p>\r\n+        </div>\r\n+\r\n+        <div style=\"text-align: center; margin-top: 30px; color: #666;\">\r\n+            <p>Merci de votre confiance!</p>\r\n+            <p>Si vous avez des questions, n'hésitez pas à nous contacter.</p>\r\n+        </div>\r\n+    </div>\r\n+</body>\r\n+</html>\n\\ No newline at end of file\n"
                },
                {
                    "date": 1740087194854,
                    "content": "Index: \n===================================================================\n--- \n+++ \n@@ -44,9 +44,9 @@\n             <p>Bonjour {{ user.get_full_name }},</p>\r\n         </div>\r\n \r\n         <div class=\"order-details\">\r\n-            <h2>Détails de votre commande #{{ commande.id }}</h2>\r\n+            <h2>Détails de votre commande #{{ commande.ref }}</h2>\r\n             <p><strong>Date:</strong> {{ date }}</p>\r\n             <p><strong>Mode de paiement:</strong> {{ commande.get_payment_method_display }}</p>\r\n         </div>\r\n \r\n"
                },
                {
                    "date": 1740087688191,
                    "content": "Index: \n===================================================================\n--- \n+++ \n@@ -1,9 +1,9 @@\n <!DOCTYPE html>\r\n <html>\r\n <head>\r\n     <style>\r\n-        body { \r\n+        body {\r\n             font-family: Arial, sans-serif;\r\n             line-height: 1.6;\r\n             color: #333;\r\n         }\r\n@@ -11,89 +11,34 @@\n             max-width: 600px;\r\n             margin: 0 auto;\r\n             padding: 20px;\r\n         }\r\n-        .header {\r\n-            background-color:rgb(233, 17, 17);\r\n-            padding: 20px;\r\n+        .logo-container {\r\n             text-align: center;\r\n-            border-radius: 5px;\r\n+            margin-bottom: 20px;\r\n         }\r\n-        .order-details {\r\n-            margin: 20px 0;\r\n-            padding: 15px;\r\n-            border: 1px solid #ddd;\r\n-            border-radius: 5px;\r\n+        .logo {\r\n+            max-width: 150px;\r\n+            height: auto;\r\n         }\r\n-        .product-item {\r\n-            padding: 10px 0;\r\n-            border-bottom: 1px solid #eee;\r\n-        }\r\n-        .total {\r\n-            margin-top: 20px;\r\n-            padding: 15px;\r\n-            background-color:rgb(223, 10, 10);\r\n-            border-radius: 5px;\r\n+        .company-name {\r\n+            font-size: 24px;\r\n+            color: rgb(233, 17, 17);\r\n             font-weight: bold;\r\n+            margin: 10px 0;\r\n+            text-align: center;\r\n         }\r\n-    </style>\r\n-</head>\r\n-<body>\r\n-    <div class=\"container\">\r\n-        <div class=\"header\">\r\n-            <h1>Confirmation de commande</h1>\r\n-            <p>Bonjour {{ user.get_full_name }},</p>\r\n-        </div>\r\n-\r\n-        <div class=\"order-details\">\r\n-            <h2>Détails de votre commande #{{ commande.ref }}</h2>\r\n-            <p><strong>Date:</strong> {{ date }}</p>\r\n-            <p><strong>Mode de paiement:</strong> {{ commande.get_payment_method_display }}</p>\r\n-        </div>\r\n-\r\n-        <h3>Articles commandés:</h3>\r\n-        {% for line in order_lines %}\r\n-        <div class=\"product-item\">\r\n-            <p>\r\n-                <strong>{{ line.product.name }}</strong><br>\r\n-                Quantité: {{ line.quantity }}<br>\r\n-                Prix unitaire: {{ line.unit_price }}FCFA<br>\r\n-                Total ligne: {{ line.line_total }}fcfa\r\n-            </p>\r\n-        </div>\r\n-        {% endfor %}\r\n-\r\n-        <div class=\"total\">\r\n-            <p>Total de la commande: {{ total }}FCFA</p>\r\n-        </div>\r\n-\r\n-        <div style=\"text-align: center; margin-top: 30px; color: #666;\">\r\n-            <p>Merci de votre confiance!</p>\r\n-            <p>Si vous avez des questions, n'hésitez pas à nous contacter.</p>\r\n-        </div>\r\n-    </div>\r\n-</body>\r\n-</html>\n-<!DOCTYPE html>\r\n-<html>\r\n-<head>\r\n-    <style>\r\n-        body { \r\n-            font-family: Arial, sans-serif;\r\n-            line-height: 1.6;\r\n-            color: #333;\r\n-        }\r\n-        .container {\r\n-            max-width: 600px;\r\n-            margin: 0 auto;\r\n-            padding: 20px;\r\n-        }\r\n         .header {\r\n-            background-color: #f8f9fa;\r\n+            background-color: rgb(233, 17, 17);\r\n             padding: 20px;\r\n             text-align: center;\r\n             border-radius: 5px;\r\n+            color: white;\r\n         }\r\n+        .header h1, .header p {\r\n+            color: white;\r\n+            margin: 10px 0;\r\n+        }\r\n         .order-details {\r\n             margin: 20px 0;\r\n             padding: 15px;\r\n             border: 1px solid #ddd;\r\n@@ -105,23 +50,36 @@\n         }\r\n         .total {\r\n             margin-top: 20px;\r\n             padding: 15px;\r\n-            background-color: #f8f9fa;\r\n+            background-color: rgb(223, 10, 10);\r\n             border-radius: 5px;\r\n             font-weight: bold;\r\n+            color: white;\r\n         }\r\n+        .footer {\r\n+            text-align: center;\r\n+            margin-top: 30px;\r\n+            color: #666;\r\n+            border-top: 2px solid rgb(233, 17, 17);\r\n+            padding-top: 20px;\r\n+        }\r\n     </style>\r\n </head>\r\n <body>\r\n     <div class=\"container\">\r\n+        <div class=\"logo-container\">\r\n+            <img src=\"/api/placeholder/150/150\" alt=\"Ghisilaine Cosmetic Logo\" class=\"logo\">\r\n+            <div class=\"company-name\">Ghisilaine Cosmetic</div>\r\n+        </div>\r\n+        \r\n         <div class=\"header\">\r\n             <h1>Confirmation de commande</h1>\r\n             <p>Bonjour {{ user.get_full_name }},</p>\r\n         </div>\r\n \r\n         <div class=\"order-details\">\r\n-            <h2>Détails de votre commande #{{ commande.id }}</h2>\r\n+            <h2>Détails de votre commande #{{ commande.ref }}</h2>\r\n             <p><strong>Date:</strong> {{ date }}</p>\r\n             <p><strong>Mode de paiement:</strong> {{ commande.get_payment_method_display }}</p>\r\n         </div>\r\n \r\n@@ -131,20 +89,23 @@\n             <p>\r\n                 <strong>{{ line.product.name }}</strong><br>\r\n                 Quantité: {{ line.quantity }}<br>\r\n                 Prix unitaire: {{ line.unit_price }}FCFA<br>\r\n-                Total ligne: {{ line.line_total }}fcfa\r\n+                Total ligne: {{ line.line_total }}FCFA\r\n             </p>\r\n         </div>\r\n         {% endfor %}\r\n \r\n         <div class=\"total\">\r\n             <p>Total de la commande: {{ total }}FCFA</p>\r\n         </div>\r\n \r\n-        <div style=\"text-align: center; margin-top: 30px; color: #666;\">\r\n-            <p>Merci de votre confiance!</p>\r\n+        <div class=\"footer\">\r\n+            <p><strong>Ghisilaine Cosmetic</strong></p>\r\n+            <p>Votre partenaire beauté de confiance</p>\r\n             <p>Si vous avez des questions, n'hésitez pas à nous contacter.</p>\r\n+            <p>Tél: +225 24 1010 010</p>\r\n+            <p>Email: GhisilaineCosmetique@gmail.com</p>\r\n         </div>\r\n     </div>\r\n </body>\r\n </html>\n\\ No newline at end of file\n"
                },
                {
                    "date": 1740087851135,
                    "content": "Index: \n===================================================================\n--- \n+++ \n@@ -67,9 +67,9 @@\n </head>\r\n <body>\r\n     <div class=\"container\">\r\n         <div class=\"logo-container\">\r\n-            <img src=\"/api/placeholder/150/150\" alt=\"Ghisilaine Cosmetic Logo\" class=\"logo\">\r\n+            <img src=\"/ghislaine-icon.png\" alt=\"Ghisilaine Cosmetic Logo\" class=\"logo\">\r\n             <div class=\"company-name\">Ghisilaine Cosmetic</div>\r\n         </div>\r\n         \r\n         <div class=\"header\">\r\n"
                },
                {
                    "date": 1740088233923,
                    "content": "Index: \n===================================================================\n--- \n+++ \n@@ -67,9 +67,9 @@\n </head>\r\n <body>\r\n     <div class=\"container\">\r\n         <div class=\"logo-container\">\r\n-            <img src=\"/ghislaine-icon.png\" alt=\"Ghisilaine Cosmetic Logo\" class=\"logo\">\r\n+            <img src=\"ghislaine-icon.png\" alt=\"Ghisilaine Cosmetic Logo\" class=\"logo\">\r\n             <div class=\"company-name\">Ghisilaine Cosmetic</div>\r\n         </div>\r\n         \r\n         <div class=\"header\">\r\n"
                },
                {
                    "date": 1740088740044,
                    "content": "Index: \n===================================================================\n--- \n+++ \n@@ -67,9 +67,9 @@\n </head>\r\n <body>\r\n     <div class=\"container\">\r\n         <div class=\"logo-container\">\r\n-            <img src=\"ghislaine-icon.png\" alt=\"Ghisilaine Cosmetic Logo\" class=\"logo\">\r\n+            <img src=\"logo.png\" alt=\"Ghisilaine Cosmetic Logo\" class=\"logo\">\r\n             <div class=\"company-name\">Ghisilaine Cosmetic</div>\r\n         </div>\r\n         \r\n         <div class=\"header\">\r\n"
                },
                {
                    "date": 1740089113186,
                    "content": "Index: \n===================================================================\n--- \n+++ \n@@ -67,9 +67,9 @@\n </head>\r\n <body>\r\n     <div class=\"container\">\r\n         <div class=\"logo-container\">\r\n-            <img src=\"logo.png\" alt=\"Ghisilaine Cosmetic Logo\" class=\"logo\">\r\n+            <img src=\"{{ logo }}\" alt=\"Ghisilaine Cosmetic Logo\" class=\"logo\">\r\n             <div class=\"company-name\">Ghisilaine Cosmetic</div>\r\n         </div>\r\n         \r\n         <div class=\"header\">\r\n"
                }
            ],
            "date": 1740075666055,
            "name": "Commit-0",
            "content": "<!DOCTYPE html>\r\n<html>\r\n<head>\r\n    <style>\r\n        body { font-family: Arial, sans-serif; line-height: 1.6; }\r\n        .container { max-width: 600px; margin: 0 auto; padding: 20px; }\r\n        .header { text-align: center; padding: 20px 0; }\r\n        .order-details { margin: 20px 0; }\r\n        .product-list { margin: 20px 0; }\r\n        .product-item { padding: 10px 0; border-bottom: 1px solid #eee; }\r\n        .total { margin-top: 20px; font-weight: bold; }\r\n        .footer { text-align: center; margin-top: 30px; color: #666; }\r\n    </style>\r\n</head>\r\n<body>\r\n    <div class=\"container\">\r\n        <div class=\"header\">\r\n            <h1>Confirmation de commande</h1>\r\n            <p>Merci pour votre commande!</p>\r\n        </div>\r\n\r\n        <div class=\"order-details\">\r\n            <p><strong>Référence:</strong> {{ commande.reference }}</p>\r\n            <p><strong>Date:</strong> {{ date }}</p>\r\n            <p><strong>Mode de paiement:</strong> {{ mode_paiement }}</p>\r\n        </div>\r\n\r\n        <div class=\"product-list\">\r\n            <h2>Articles commandés:</h2>\r\n            {% for article in articles %}\r\n            <div class=\"product-item\">\r\n                <p>\r\n                    <strong>{{ article.produit.nom }}</strong><br>\r\n                    Quantité: {{ article.quantite }}<br>\r\n                    Prix unitaire: {{ article.prix_unitaire }}FCFA<br>\r\n                    Total: {{ article.prix_total }} FCFA\r\n                </p>\r\n            </div>\r\n            {% endfor %}\r\n        </div>\r\n\r\n        <div class=\"total\">\r\n            <p>Total de la commande: {{ total }}FCFA</p>\r\n        </div>\r\n\r\n        <div class=\"footer\">\r\n            <p>En cas de question, n'hésitez pas à nous contacter.</p>\r\n            <p>Merci de votre confiance!</p>\r\n        </div>\r\n    </div>\r\n</body>\r\n</html>"
        }
    ]
}